{"countryCode":"NP","countryName":"Nepal","countryFilePath":"NP.json","countryCityList":[{"_id":1283378,"name":"Gorkhā","country":"NP","coord":{"lon":84.633331,"lat":28.0}},{"_id":1283710,"name":"Bāgmatī Zone","country":"NP","coord":{"lon":85.416664,"lat":28.0}},{"_id":1283240,"name":"Kathmandu","country":"NP","coord":{"lon":85.316666,"lat":27.716667}},{"_id":1282635,"name":"Tulsipur","country":"NP","coord":{"lon":82.297256,"lat":28.130989}},{"_id":6941685,"name":"Pisang","country":"NP","coord":{"lon":84.147202,"lat":28.614647}},{"_id":1282682,"name":"Thapathali","country":"NP","coord":{"lon":85.316666,"lat":27.716667}},{"_id":1283076,"name":"Manangbhot","country":"NP","coord":{"lon":84.01667,"lat":28.666668}},{"_id":1283150,"name":"Lamjung","country":"NP","coord":{"lon":84.366669,"lat":28.200001}},{"_id":1282940,"name":"Parāsi","country":"NP","coord":{"lon":83.666664,"lat":27.533333}},{"_id":1283692,"name":"Bālāju","country":"NP","coord":{"lon":85.300003,"lat":27.733334}},{"_id":7113953,"name":"Thamel","country":"NP","coord":{"lon":85.310211,"lat":27.715141}},{"_id":1282898,"name":"Pokhara","country":"NP","coord":{"lon":83.98333,"lat":28.233334}},{"_id":1283295,"name":"Jomosom","country":"NP","coord":{"lon":83.73333,"lat":28.783333}},{"_id":1282748,"name":"Sunauli","country":"NP","coord":{"lon":83.416664,"lat":27.5}},{"_id":1282933,"name":"Pashupatināth","country":"NP","coord":{"lon":85.349998,"lat":27.700001}},{"_id":7800118,"name":"Nagarkot","country":"NP","coord":{"lon":85.503098,"lat":27.713699}},{"_id":1282616,"name":"Waling","country":"NP","coord":{"lon":83.76667,"lat":27.98333}},{"_id":1282666,"name":"Tikapur","country":"NP","coord":{"lon":81.133331,"lat":28.5}},{"_id":1282714,"name":"Tansen","country":"NP","coord":{"lon":83.5467,"lat":27.86731}},{"_id":1282770,"name":"Siraha","country":"NP","coord":{"lon":86.208702,"lat":26.65411}},{"_id":1282884,"name":"Rajbiraj","country":"NP","coord":{"lon":86.75,"lat":26.533331}},{"_id":1282950,"name":"Panaoti","country":"NP","coord":{"lon":85.512398,"lat":27.581381}},{"_id":1283082,"name":"Malangwa","country":"NP","coord":{"lon":85.558113,"lat":26.856791}},{"_id":1283095,"name":"Mahendranagar","country":"NP","coord":{"lon":80.333328,"lat":28.91667}},{"_id":1283161,"name":"Lahan","country":"NP","coord":{"lon":86.495148,"lat":26.72958}},{"_id":1283217,"name":"Khandbari","country":"NP","coord":{"lon":87.203903,"lat":27.374689}},{"_id":1283318,"name":"Janakpur","country":"NP","coord":{"lon":85.906464,"lat":26.718281}},{"_id":1283323,"name":"Jaleswar","country":"NP","coord":{"lon":85.800812,"lat":26.64711}},{"_id":1283329,"name":"Ithari","country":"NP","coord":{"lon":87.283333,"lat":26.66667}},{"_id":1283334,"name":"Ilām","country":"NP","coord":{"lon":87.916672,"lat":26.91667}},{"_id":1283333,"name":"Ilam","country":"NP","coord":{"lon":87.928238,"lat":26.90943}},{"_id":1283339,"name":"Hitura","country":"NP","coord":{"lon":85.032188,"lat":27.428391}},{"_id":1283368,"name":"Gulariya","country":"NP","coord":{"lon":81.333328,"lat":28.23333}},{"_id":1283401,"name":"Gaur","country":"NP","coord":{"lon":85.26667,"lat":26.76667}},{"_id":1283460,"name":"Dharan Bazar","country":"NP","coord":{"lon":87.283546,"lat":26.812481}},{"_id":1283465,"name":"Dhankuta","country":"NP","coord":{"lon":87.333328,"lat":26.98333}},{"_id":1283467,"name":"Dhangarhi","country":"NP","coord":{"lon":80.596107,"lat":28.70792}},{"_id":1283484,"name":"Darchula","country":"NP","coord":{"lon":80.52874,"lat":29.841209}},{"_id":1283497,"name":"Dailekh","country":"NP","coord":{"lon":81.666672,"lat":28.83333}},{"_id":1283496,"name":"Dailekh","country":"NP","coord":{"lon":81.710114,"lat":28.844339}},{"_id":1283499,"name":"Dadeldhura","country":"NP","coord":{"lon":80.580589,"lat":29.29842}},{"_id":1283562,"name":"Butwal","country":"NP","coord":{"lon":83.448357,"lat":27.70055}},{"_id":1283581,"name":"Birganj","country":"NP","coord":{"lon":84.87735,"lat":27.010429}},{"_id":1283628,"name":"Bhadrapur","country":"NP","coord":{"lon":88.09436,"lat":26.544041}},{"_id":1283679,"name":"Banepa","country":"NP","coord":{"lon":85.521378,"lat":27.629789}},{"_id":1283711,"name":"Baglung","country":"NP","coord":{"lon":83.58976,"lat":28.271891}},{"_id":6254843,"name":"Birendranagar","country":"NP","coord":{"lon":81.633888,"lat":28.60194}},{"_id":1282988,"name":"Kingdom of Nepal","country":"NP","coord":{"lon":84.0,"lat":28.0}},{"_id":6941672,"name":"Eklobhati","country":"NP","coord":{"lon":83.773842,"lat":28.818281}},{"_id":1283278,"name":"Kāgbeni","country":"NP","coord":{"lon":83.783333,"lat":28.833332}},{"_id":6941675,"name":"Khingar","country":"NP","coord":{"lon":83.829529,"lat":28.821741}},{"_id":6941673,"name":"Jharkot","country":"NP","coord":{"lon":83.848106,"lat":28.819372}},{"_id":1283031,"name":"Muktināth","country":"NP","coord":{"lon":83.883331,"lat":28.816668}},{"_id":1283213,"name":"Khāngsar","country":"NP","coord":{"lon":83.98333,"lat":28.683332}},{"_id":6941681,"name":"Braga","country":"NP","coord":{"lon":84.036827,"lat":28.658733}},{"_id":6941683,"name":"Hongde","country":"NP","coord":{"lon":84.087379,"lat":28.641411}},{"_id":6941687,"name":"Ghyaru","country":"NP","coord":{"lon":84.137505,"lat":28.642143}},{"_id":6941686,"name":"Upper Pisang","country":"NP","coord":{"lon":84.153664,"lat":28.616266}},{"_id":6941688,"name":"Bhratang","country":"NP","coord":{"lon":84.190163,"lat":28.572914}},{"_id":6941689,"name":"Chame","country":"NP","coord":{"lon":84.250977,"lat":28.553692}},{"_id":1282676,"name":"Thonje","country":"NP","coord":{"lon":84.349998,"lat":28.516666}},{"_id":1282731,"name":"Tāgring","country":"NP","coord":{"lon":84.383331,"lat":28.35}},{"_id":6254841,"name":"Thulobeshi","country":"NP","coord":{"lon":84.419167,"lat":28.333889}},{"_id":6941690,"name":"Khudi","country":"NP","coord":{"lon":84.359123,"lat":28.282162}},{"_id":1283038,"name":"Muglaha","country":"NP","coord":{"lon":83.23333,"lat":27.483334}},{"_id":1282839,"name":"Rummin-dei","country":"NP","coord":{"lon":83.283333,"lat":27.483334}},{"_id":1283621,"name":"Bhairahawa","country":"NP","coord":{"lon":83.449997,"lat":27.5}},{"_id":1282724,"name":"Tamāspur","country":"NP","coord":{"lon":83.949997,"lat":27.566668}},{"_id":1283006,"name":"Nandpur","country":"NP","coord":{"lon":84.033333,"lat":27.566668}},{"_id":1283522,"name":"Chilha","country":"NP","coord":{"lon":84.116669,"lat":27.616667}},{"_id":1283046,"name":"Meghauli","country":"NP","coord":{"lon":84.23333,"lat":27.583332}},{"_id":1283049,"name":"Maruwā Ghāt","country":"NP","coord":{"lon":84.400002,"lat":27.700001}},{"_id":1283001,"name":"Nārāyangarh","country":"NP","coord":{"lon":84.416664,"lat":27.683332}},{"_id":1283613,"name":"Bharatpur","country":"NP","coord":{"lon":84.433334,"lat":27.683332}},{"_id":1282665,"name":"Tikoli","country":"NP","coord":{"lon":84.5,"lat":27.633333}},{"_id":1282621,"name":"Upardāng Garhi","country":"NP","coord":{"lon":84.566666,"lat":27.766666}},{"_id":1283256,"name":"Kāndrāng Garhi","country":"NP","coord":{"lon":84.783333,"lat":27.716667}},{"_id":1282951,"name":"Pālung","country":"NP","coord":{"lon":85.066666,"lat":27.633333}},{"_id":1282996,"name":"Naubise","country":"NP","coord":{"lon":85.150002,"lat":27.716667}},{"_id":1282684,"name":"Thānkot","country":"NP","coord":{"lon":85.183334,"lat":27.683332}},{"_id":1283190,"name":"Kirtipur","country":"NP","coord":{"lon":85.283333,"lat":27.666668}},{"_id":1283312,"name":"Jawlakhel","country":"NP","coord":{"lon":85.316666,"lat":27.666668}},{"_id":1282931,"name":"Patan","country":"NP","coord":{"lon":85.333336,"lat":27.666668}},{"_id":1283678,"name":"Bāneswar","country":"NP","coord":{"lon":85.333336,"lat":27.683332}},{"_id":1282976,"name":"Nougām","country":"NP","coord":{"lon":85.26667,"lat":27.666668}},{"_id":1283422,"name":"Dumān","country":"NP","coord":{"lon":85.116669,"lat":27.683332}},{"_id":1283471,"name":"Dhāding","country":"NP","coord":{"lon":84.916664,"lat":27.866667}},{"_id":1283636,"name":"Benighāt","country":"NP","coord":{"lon":84.783333,"lat":27.816668}},{"_id":1283088,"name":"Makaising","country":"NP","coord":{"lon":84.683334,"lat":27.883333}},{"_id":1283680,"name":"Bandīpur","country":"NP","coord":{"lon":84.416664,"lat":27.933332}},{"_id":1282721,"name":"Tanahun","country":"NP","coord":{"lon":84.333336,"lat":28.033333}},{"_id":1282766,"name":"Sisāghāt Bāzār","country":"NP","coord":{"lon":84.25,"lat":28.083332}},{"_id":1283651,"name":"Bathāla","country":"NP","coord":{"lon":84.066666,"lat":28.049999}},{"_id":1283474,"name":"Deorāli","country":"NP","coord":{"lon":84.166664,"lat":28.116667}},{"_id":1282869,"name":"Rānīpauwa","country":"NP","coord":{"lon":84.0,"lat":28.216667}},{"_id":1283654,"name":"Bartār","country":"NP","coord":{"lon":84.433334,"lat":28.116667}},{"_id":1282679,"name":"Thāre Pāti","country":"NP","coord":{"lon":85.5,"lat":28.016666}},{"_id":1283113,"name":"Lukla","country":"NP","coord":{"lon":86.716667,"lat":27.700001}},{"_id":1283011,"name":"Namche Bazar","country":"NP","coord":{"lon":86.716667,"lat":27.816668}},{"_id":1282670,"name":"Thyāngboche","country":"NP","coord":{"lon":86.76667,"lat":27.833332}},{"_id":1283044,"name":"Mingbo","country":"NP","coord":{"lon":86.816666,"lat":27.85}},{"_id":1283437,"name":"Dingboche","country":"NP","coord":{"lon":86.833336,"lat":27.9}},{"_id":1282673,"name":"Thukla","country":"NP","coord":{"lon":86.800003,"lat":27.916668}},{"_id":1283119,"name":"Lobujya","country":"NP","coord":{"lon":86.816666,"lat":27.950001}},{"_id":1282913,"name":"Phorcha","country":"NP","coord":{"lon":86.75,"lat":27.85}},{"_id":1283524,"name":"Chhule","country":"NP","coord":{"lon":86.616669,"lat":27.950001}},{"_id":6941095,"name":"Dole","country":"NP","coord":{"lon":86.716667,"lat":27.833332}},{"_id":1282945,"name":"Pangboche","country":"NP","coord":{"lon":86.800003,"lat":27.85}},{"_id":1283290,"name":"Jubing","country":"NP","coord":{"lon":86.699997,"lat":27.583332}},{"_id":1283284,"name":"Junbesi","country":"NP","coord":{"lon":86.533333,"lat":27.583332}},{"_id":1282860,"name":"Rasnālu","country":"NP","coord":{"lon":86.199997,"lat":27.566668}},{"_id":1282671,"name":"Thulopātāl","country":"NP","coord":{"lon":86.166664,"lat":27.6}},{"_id":1283192,"name":"Kirāntīchhāp","country":"NP","coord":{"lon":86.066666,"lat":27.633333}},{"_id":1283546,"name":"Charikot","country":"NP","coord":{"lon":86.033333,"lat":27.666668}},{"_id":1282720,"name":"Tāndi","country":"NP","coord":{"lon":85.916664,"lat":27.633333}},{"_id":1283429,"name":"Dolālghāt","country":"NP","coord":{"lon":85.699997,"lat":27.65}},{"_id":1282948,"name":"Panchkhal","country":"NP","coord":{"lon":85.616669,"lat":27.65}},{"_id":1283018,"name":"Nagarkot","country":"NP","coord":{"lon":85.51667,"lat":27.700001}},{"_id":1282813,"name":"Sānkhu","country":"NP","coord":{"lon":85.449997,"lat":27.716667}},{"_id":1283647,"name":"Baudhatinchule","country":"NP","coord":{"lon":85.366669,"lat":27.716667}},{"_id":1282677,"name":"Thimi","country":"NP","coord":{"lon":85.383331,"lat":27.683332}},{"_id":1283618,"name":"Bhaktapur","country":"NP","coord":{"lon":85.416725,"lat":27.667337}},{"_id":1283540,"name":"Chaunrikharka","country":"NP","coord":{"lon":86.716667,"lat":27.666668}},{"_id":1283616,"name":"Bhandār","country":"NP","coord":{"lon":86.349998,"lat":27.583332}},{"_id":1282675,"name":"Those","country":"NP","coord":{"lon":86.25,"lat":27.583332}},{"_id":1283617,"name":"Bhaktapur","country":"NP","coord":{"lon":85.416664,"lat":27.683332}},{"_id":1283510,"name":"Chukhung","country":"NP","coord":{"lon":86.833336,"lat":27.9}},{"_id":1283047,"name":"Mechī Zone","country":"NP","coord":{"lon":87.916664,"lat":27.166668}},{"_id":1282836,"name":"Sagarmāthā Zone","country":"NP","coord":{"lon":86.666664,"lat":27.333332}},{"_id":1283454,"name":"Dhawalāgiri Zone","country":"NP","coord":{"lon":83.5,"lat":28.833332}},{"_id":1283410,"name":"Gandakī Zone","country":"NP","coord":{"lon":84.5,"lat":28.166668}},{"_id":7289709,"name":"Pashchimanchal","country":"NP","coord":{"lon":83.938293,"lat":28.170389}},{"_id":1282722,"name":"Tanahun","country":"NP","coord":{"lon":84.25,"lat":27.91667}},{"_id":7801503,"name":"Bhanumati","country":"NP","coord":{"lon":84.030571,"lat":28.00094}},{"_id":8003027,"name":"Buchakhani","country":"NP","coord":{"lon":84.000778,"lat":28.00042}},{"_id":7289707,"name":"Madhyamanchal","country":"NP","coord":{"lon":85.223007,"lat":27.454359}},{"_id":1282973,"name":"Nuwākot","country":"NP","coord":{"lon":85.25,"lat":27.91667}},{"_id":7802136,"name":"Ghyangphedi","country":"NP","coord":{"lon":85.439941,"lat":27.989901}},{"_id":7974073,"name":"Lampate","country":"NP","coord":{"lon":85.424698,"lat":27.985451}},{"_id":1283379,"name":"Gorkhā","country":"NP","coord":{"lon":84.833328,"lat":28.33333}},{"_id":7799297,"name":"PrithbinarayanN.P.","country":"NP","coord":{"lon":84.605301,"lat":27.9804}},{"_id":7949204,"name":"(Pokharithok Bajar)","country":"NP","coord":{"lon":84.630653,"lat":27.996189}},{"_id":1283077,"name":"Manang","country":"NP","coord":{"lon":84.25,"lat":28.66667}},{"_id":7802063,"name":"Pisang","country":"NP","coord":{"lon":84.149063,"lat":28.597429}},{"_id":1283243,"name":"Kāskī","country":"NP","coord":{"lon":84.0,"lat":28.33333}},{"_id":7801962,"name":"PokharaN.P.","country":"NP","coord":{"lon":83.99218,"lat":28.21386}},{"_id":7961335,"name":"Nalamukh","country":"NP","coord":{"lon":83.98391,"lat":28.231001}},{"_id":1283023,"name":"Mustāng","country":"NP","coord":{"lon":83.916672,"lat":28.91667}},{"_id":7800940,"name":"Jomsom","country":"NP","coord":{"lon":83.770432,"lat":28.76696}},{"_id":7910491,"name":"Jomsom","country":"NP","coord":{"lon":83.73513,"lat":28.784361}},{"_id":1283151,"name":"Lamjung","country":"NP","coord":{"lon":84.416672,"lat":28.25}},{"_id":7800858,"name":"Gaunshahar","country":"NP","coord":{"lon":84.380539,"lat":28.20573}},{"_id":7966485,"name":"Khatrigaun","country":"NP","coord":{"lon":84.371452,"lat":28.199881}},{"_id":7800941,"name":"Kagbeni","country":"NP","coord":{"lon":83.727898,"lat":28.849649}},{"_id":7971832,"name":"Kagbenee","country":"NP","coord":{"lon":83.787109,"lat":28.83882}},{"_id":7800933,"name":"Khangsar","country":"NP","coord":{"lon":83.925346,"lat":28.660391}},{"_id":7969462,"name":"Chyongo","country":"NP","coord":{"lon":83.975517,"lat":28.67861}},{"_id":7802061,"name":"Chame","country":"NP","coord":{"lon":84.269928,"lat":28.5338}},{"_id":7800877,"name":"Taghring","country":"NP","coord":{"lon":84.381828,"lat":28.370001}},{"_id":7967083,"name":"Gairigaun","country":"NP","coord":{"lon":84.381203,"lat":28.34211}},{"_id":7801994,"name":"Khudi","country":"NP","coord":{"lon":84.36631,"lat":28.32102}},{"_id":1283112,"name":"Lumbinī Zone","country":"NP","coord":{"lon":83.5,"lat":27.75}},{"_id":1282837,"name":"Rūpandehī","country":"NP","coord":{"lon":83.416672,"lat":27.66667}},{"_id":7802360,"name":"SiddharthNagarN.P.","country":"NP","coord":{"lon":83.448341,"lat":27.502661}},{"_id":1282991,"name":"Nawalparāsī","country":"NP","coord":{"lon":83.916672,"lat":27.66667}},{"_id":7800988,"name":"RamgramN.P.","country":"NP","coord":{"lon":83.6735,"lat":27.52935}},{"_id":7973340,"name":"Ghodpali","country":"NP","coord":{"lon":83.661621,"lat":27.52878}},{"_id":7802106,"name":"Kolhuwa","country":"NP","coord":{"lon":84.059471,"lat":27.57535}},{"_id":7973056,"name":"Nandapur","country":"NP","coord":{"lon":84.037491,"lat":27.56111}},{"_id":7802105,"name":"Kawaswoti","country":"NP","coord":{"lon":84.127563,"lat":27.61747}},{"_id":7973039,"name":"Makarkot","country":"NP","coord":{"lon":84.117218,"lat":27.622061}},{"_id":7801829,"name":"Gaidakot","country":"NP","coord":{"lon":84.396339,"lat":27.707899}},{"_id":7972960,"name":"Madhuwaghat","country":"NP","coord":{"lon":84.400383,"lat":27.70216}},{"_id":1283000,"name":"Nārāyanī Zone","country":"NP","coord":{"lon":84.916672,"lat":27.366671}},{"_id":1283517,"name":"Chitawan","country":"NP","coord":{"lon":84.5,"lat":27.58333}},{"_id":7800545,"name":"Dahakhani","country":"NP","coord":{"lon":84.54248,"lat":27.77109}},{"_id":7934341,"name":"Dharsin","country":"NP","coord":{"lon":84.563408,"lat":27.764071}},{"_id":1283472,"name":"Dhāding","country":"NP","coord":{"lon":84.916672,"lat":28.0}},{"_id":7799586,"name":"Naubise","country":"NP","coord":{"lon":85.156998,"lat":27.703199}},{"_id":7942140,"name":"Kattichhap","country":"NP","coord":{"lon":85.1492,"lat":27.71784}},{"_id":1283085,"name":"Makwānpur","country":"NP","coord":{"lon":85.25,"lat":27.41667}},{"_id":7802044,"name":"Chitlang","country":"NP","coord":{"lon":85.169281,"lat":27.647539}},{"_id":7968003,"name":"Dandakhrka","country":"NP","coord":{"lon":85.18428,"lat":27.67441}},{"_id":1282946,"name":"Pānga","country":"NP","coord":{"lon":85.283333,"lat":27.66667}},{"_id":1283154,"name":"Lalitpur","country":"NP","coord":{"lon":85.333328,"lat":27.58333}},{"_id":7799973,"name":"LalitpurN.P.","country":"NP","coord":{"lon":85.319901,"lat":27.6691}},{"_id":7965675,"name":"Gwarko","country":"NP","coord":{"lon":85.335037,"lat":27.666599}},{"_id":1283241,"name":"Kathmandu","country":"NP","coord":{"lon":85.416672,"lat":27.75}},{"_id":7800827,"name":"KathmanduN.P.","country":"NP","coord":{"lon":85.322182,"lat":27.70731}},{"_id":7962239,"name":"Shankhamul Dobhan","country":"NP","coord":{"lon":85.334251,"lat":27.680861}},{"_id":7799674,"name":"Sunaulabazar","country":"NP","coord":{"lon":84.911102,"lat":27.870199}},{"_id":7942462,"name":"Kusunde","country":"NP","coord":{"lon":84.913887,"lat":27.864161}},{"_id":7802653,"name":"Tanahunsur","country":"NP","coord":{"lon":84.334641,"lat":28.036249}},{"_id":8004777,"name":"Patyarthok","country":"NP","coord":{"lon":84.334068,"lat":28.03129}},{"_id":7801509,"name":"Kyamin","country":"NP","coord":{"lon":84.267509,"lat":28.060459}},{"_id":8004101,"name":"Baniya Dihi","country":"NP","coord":{"lon":84.25209,"lat":28.084221}},{"_id":7801505,"name":"Dhorfirdi","country":"NP","coord":{"lon":84.030937,"lat":28.05267}},{"_id":8003390,"name":"Ganapati","country":"NP","coord":{"lon":84.063431,"lat":28.051809}},{"_id":7800254,"name":"Deurali","country":"NP","coord":{"lon":84.153458,"lat":28.118429}},{"_id":7960439,"name":"Kusunde","country":"NP","coord":{"lon":84.168121,"lat":28.122789}},{"_id":7800876,"name":"Sundarbazar","country":"NP","coord":{"lon":84.419907,"lat":28.13188}},{"_id":7967031,"name":"Paundidhik Bajar","country":"NP","coord":{"lon":84.429062,"lat":28.114571}},{"_id":7647006,"name":"Sindhupalchok","country":"NP","coord":{"lon":85.545036,"lat":27.829359}},{"_id":7801335,"name":"Helumbu","country":"NP","coord":{"lon":85.54435,"lat":27.993549}},{"_id":7994717,"name":"Panchosa","country":"NP","coord":{"lon":85.507423,"lat":28.0037}},{"_id":7289708,"name":"Purwanchal","country":"NP","coord":{"lon":87.148018,"lat":27.239981}},{"_id":1282758,"name":"Solukhumbū","country":"NP","coord":{"lon":86.75,"lat":27.75}},{"_id":7802556,"name":"Chaurikharka","country":"NP","coord":{"lon":86.736519,"lat":27.7139}},{"_id":7996530,"name":"Chaurikharka","country":"NP","coord":{"lon":86.721741,"lat":27.697809}},{"_id":7801416,"name":"Khumjung","country":"NP","coord":{"lon":86.757339,"lat":27.87332}},{"_id":7996816,"name":"Jaro","country":"NP","coord":{"lon":86.713219,"lat":27.81604}},{"_id":7996820,"name":"Thyanboche","country":"NP","coord":{"lon":86.768822,"lat":27.837379}},{"_id":7996828,"name":"Minbo","country":"NP","coord":{"lon":86.822388,"lat":27.85405}},{"_id":7996839,"name":"Dinboche","country":"NP","coord":{"lon":86.837059,"lat":27.8964}},{"_id":7996868,"name":"Phorche","country":"NP","coord":{"lon":86.752823,"lat":27.849939}},{"_id":7801420,"name":"Namche","country":"NP","coord":{"lon":86.666191,"lat":27.83148}},{"_id":7997059,"name":"Chhulung Marsaang","country":"NP","coord":{"lon":86.610863,"lat":27.94282}},{"_id":7800110,"name":"Kautunje","country":"NP","coord":{"lon":85.411499,"lat":27.663601}},{"_id":1283182,"name":"Kosī Zone","country":"NP","coord":{"lon":87.316673,"lat":27.15}},{"_id":1283712,"name":"Bāglung","country":"NP","coord":{"lon":83.166672,"lat":28.41667}},{"_id":7962279,"name":"Sinamangal","country":"NP","coord":{"lon":85.354942,"lat":27.69632}},{"_id":8010237,"name":"Banachaur","country":"NP","coord":{"lon":85.415756,"lat":27.666161}},{"_id":1283582,"name":"Biratnagar","country":"NP","coord":{"lon":87.283371,"lat":26.483101}},{"_id":1283316,"name":"Janakpur Zone","country":"NP","coord":{"lon":86.0,"lat":27.33333}},{"_id":7648379,"name":"Dhanusa","country":"NP","coord":{"lon":86.010002,"lat":26.83}},{"_id":7800051,"name":"Basahiya","country":"NP","coord":{"lon":85.911797,"lat":26.6961}},{"_id":7943571,"name":"Basahiya","country":"NP","coord":{"lon":85.913887,"lat":26.69743}},{"_id":7800283,"name":"Darling","country":"NP","coord":{"lon":83.589157,"lat":28.27663}},{"_id":7953967,"name":"Ramrekha","country":"NP","coord":{"lon":83.605827,"lat":28.26368}},{"_id":7289706,"name":"Madhya Pashchimanchal","country":"NP","coord":{"lon":82.313347,"lat":29.059771}},{"_id":1283606,"name":"Bherī Zone","country":"NP","coord":{"lon":81.666672,"lat":28.58333}},{"_id":6941099,"name":"Nepalgunj","country":"NP","coord":{"lon":81.616669,"lat":28.049999}},{"_id":1283040,"name":"Morang","country":"NP","coord":{"lon":87.5,"lat":26.66667}},{"_id":7799185,"name":"BiratnagarN.P.","country":"NP","coord":{"lon":87.274101,"lat":26.452499}},{"_id":7970003,"name":"Airport","country":"NP","coord":{"lon":87.27092,"lat":26.484381}},{"_id":1282938,"name":"Parsa","country":"NP","coord":{"lon":84.833328,"lat":27.33333}},{"_id":7801091,"name":"Nirmalbasti","country":"NP","coord":{"lon":84.671509,"lat":27.30599}},{"_id":7979462,"name":"Odar","country":"NP","coord":{"lon":84.654846,"lat":27.322781}},{"_id":7667450,"name":"Surkhet","country":"NP","coord":{"lon":81.778702,"lat":28.51746}},{"_id":7801451,"name":"BirendranagarN.P.","country":"NP","coord":{"lon":81.619041,"lat":28.61198}},{"_id":7998675,"name":"Khajura","country":"NP","coord":{"lon":81.63163,"lat":28.58744}},{"_id":1283670,"name":"Bārā","country":"NP","coord":{"lon":85.083328,"lat":27.08333}},{"_id":7799408,"name":"PiparaSimara","country":"NP","coord":{"lon":85.005898,"lat":27.1912}},{"_id":8009059,"name":"Auraha","country":"NP","coord":{"lon":84.987831,"lat":27.15839}},{"_id":7961377,"name":"Syaldule","country":"NP","coord":{"lon":83.981262,"lat":28.19623}},{"_id":1283245,"name":"Karnālī Zone","country":"NP","coord":{"lon":82.416672,"lat":29.5}},{"_id":1283287,"name":"Jumla","country":"NP","coord":{"lon":82.183327,"lat":29.27528}},{"_id":7798776,"name":"Chandannath","country":"NP","coord":{"lon":82.175598,"lat":29.315201}},{"_id":7955603,"name":"Talichaur","country":"NP","coord":{"lon":82.193932,"lat":29.273291}},{"_id":1282826,"name":"Salyan","country":"NP","coord":{"lon":82.170303,"lat":28.37858}},{"_id":1282878,"name":"Ramechhap","country":"NP","coord":{"lon":86.087677,"lat":27.3256}},{"_id":1282887,"name":"Pyuthan","country":"NP","coord":{"lon":82.88427,"lat":28.088671}},{"_id":1283189,"name":"Kodari","country":"NP","coord":{"lon":85.948471,"lat":27.952511}},{"_id":1283285,"name":"Jumla","country":"NP","coord":{"lon":82.18383,"lat":29.274719}},{"_id":1283599,"name":"Bhojpur","country":"NP","coord":{"lon":81.775551,"lat":27.93565}},{"_id":1283600,"name":"Bhojpur","country":"NP","coord":{"lon":87.046066,"lat":27.171499}},{"_id":1283662,"name":"Bardiya","country":"NP","coord":{"lon":81.3536,"lat":28.300579}},{"_id":1283742,"name":"Achham","country":"NP","coord":{"lon":81.300003,"lat":29.049999}},{"_id":6254845,"name":"Dipayal","country":"NP","coord":{"lon":80.940002,"lat":29.26083}},{"_id":6941691,"name":"Chitre","country":"NP","coord":{"lon":83.690758,"lat":28.426729}},{"_id":7649119,"name":"Surkhet","country":"NP","coord":{"lon":81.778702,"lat":28.51746}},{"_id":7969491,"name":"Nawal","country":"NP","coord":{"lon":84.102791,"lat":28.64831}},{"_id":8199102,"name":"kankrabari Dovan","country":"NP","coord":{"lon":85.459343,"lat":27.628811}}]}
