{"countryCode":"FK","countryName":"Falkland Islands","countryFilePath":"FK.json","countryCityList":[{"_id":3474414,"name":"Falkland Islands (Islas Malvinas)","country":"FK","coord":{"lon":-59.166672,"lat":-51.75}},{"_id":3426691,"name":"Stanley","country":"FK","coord":{"lon":-57.849998,"lat":-51.700001}},{"_id":3426768,"name":"Rincon Grande Settlement","country":"FK","coord":{"lon":-58.30933,"lat":-51.46151}},{"_id":3426886,"name":"Mare Harbour Rancho","country":"FK","coord":{"lon":-58.400002,"lat":-51.900002}}]}
